ratelimitx/__about__.py
ratelimitx/__init__.py
ratelimitx-0.1.0.dist-info/METADATA
ratelimitx-0.1.0.dist-info/WHEEL
ratelimitx-0.1.0.dist-info/licenses/LICENSE.txt
ratelimitx-0.1.0.dist-info/RECORD
