Metadata-Version: 2.1
Name: ratelimitx
Version: 0.1.0
Project-URL: Documentation, https://github.com/rykroon/ratelimitx#readme
Project-URL: Issues, https://github.com/rykroon/ratelimitx/issues
Project-URL: Source, https://github.com/rykroon/ratelimitx
Author-email: Ryan Kroon <rykroon.tech@gmail.com>
License-Expression: MIT
License-File: LICENSE.txt
Classifier: Development Status :: 4 - Beta
Classifier: Programming Language :: Python
Classifier: Programming Language :: Python :: 3.9
Classifier: Programming Language :: Python :: 3.10
Classifier: Programming Language :: Python :: 3.11
Classifier: Programming Language :: Python :: Implementation :: CPython
Classifier: Programming Language :: Python :: Implementation :: PyPy
Requires-Python: >=3.9
Requires-Dist: redis>=4.4
